pyipfs/Constants.py
pyipfs/Errors.py
pyipfs/__init__.py
pyipfs/add.py
pyipfs/ipfs.py
pyipfs-0.1.1.dist-info/LICENSE
pyipfs-0.1.1.dist-info/METADATA
pyipfs-0.1.1.dist-info/WHEEL
pyipfs-0.1.1.dist-info/top_level.txt
pyipfs-0.1.1.dist-info/RECORD
