Metadata-Version: 2.1
Name: pyipfs
Version: 0.1.1
Summary: intract ipfs server with python
Home-page: https://github.com/codingbeast/ipfs
Author: Raaj
Author-email: Raj0kumar00@gmail.com
License: MIT License
Platform: UNKNOWN
Classifier: Development Status :: 1 - Planning
Classifier: Intended Audience :: Science/Research
Classifier: License :: OSI Approved :: MIT License
Classifier: Operating System :: POSIX :: Linux
Classifier: Programming Language :: Python :: 3
Classifier: Programming Language :: Python :: 3.4
Classifier: Programming Language :: Python :: 3.5
Requires-Dist: requests
